{
  "_class": "symbolInstance",
  "booleanOperation": -1,
  "clippingMaskMode": 0,
  "do_objectID": "52249CD9-3FBB-48EC-B059-DEFF5D977A37",
  "exportOptions": {
    "_class": "exportOptions",
    "do_objectID": "E238EC42-6CAB-420E-A7CA-1B5B8FE8A001",
    "exportFormats": [
    ],
    "includedLayerIds": [
    ],
    "layerOptions": 0,
    "shouldTrim": false
  },
  "frame": {
    "_class": "rect",
    "constrainProportions": false,
    "do_objectID": "EF984EF5-F1B7-48C5-A0AD-9423F9DA9C10",
    "height": 274,
    "width": 302,
    "x": 65,
    "y": 181
  },
  "hasClippingMask": false,
  "horizontalSpacing": 0,
  "isFixedToViewport": false,
  "isFlippedHorizontal": false,
  "isFlippedVertical": false,
  "isLocked": false,
  "isVisible": true,
  "layerListExpandedType": 0,
  "name": "MOECULE / TEXT BOXES",
  "nameIsFixed": false,
  "overrideValues": [
  ],
  "resizingConstraint": 63,
  "resizingType": 0,
  "rotation": 0,
  "scale": 1,
  "shouldBreakMaskChain": false,
  "style": {
    "_class": "style",
    "do_objectID": "8A331B4E-6BF2-4BB8-88D6-5FB3678EF7DC",
    "endMarkerType": 0,
    "miterLimit": 10,
    "startMarkerType": 0,
    "windingRule": 1
  },
  "symbolID": "AB346C1A-A281-414A-B020-9606C727A2A7",
  "verticalSpacing": 0
}