{
  "_class": "symbolInstance",
  "booleanOperation": -1,
  "clippingMaskMode": 0,
  "do_objectID": "EB17611F-47A1-4ABB-BC38-D972416DA023",
  "exportOptions": {
    "_class": "exportOptions",
    "do_objectID": "19D9F5F0-43D0-495F-AAD4-2DA3138B3038",
    "exportFormats": [
    ],
    "includedLayerIds": [
    ],
    "layerOptions": 0,
    "shouldTrim": false
  },
  "frame": {
    "_class": "rect",
    "constrainProportions": false,
    "do_objectID": "475D9766-C2F4-44B2-B71D-31E67B37F69A",
    "height": 275,
    "width": 302,
    "x": 43,
    "y": 186
  },
  "hasClippingMask": false,
  "horizontalSpacing": 0,
  "isFixedToViewport": false,
  "isFlippedHorizontal": false,
  "isFlippedVertical": false,
  "isLocked": false,
  "isVisible": true,
  "layerListExpandedType": 0,
  "name": "MOECULE / TEXT BOXES",
  "nameIsFixed": false,
  "overrideValues": [
  ],
  "resizingConstraint": 63,
  "resizingType": 0,
  "rotation": 0,
  "scale": 1,
  "shouldBreakMaskChain": false,
  "style": {
    "_class": "style",
    "do_objectID": "BDAD46E1-2690-42D2-868D-3A4F5668EDA9",
    "endMarkerType": 0,
    "miterLimit": 10,
    "startMarkerType": 0,
    "windingRule": 1
  },
  "symbolID": "8AD9FECE-4C4C-483C-85C6-06D71A5A62D9",
  "verticalSpacing": 0
}