{
  "_class": "symbolInstance",
  "booleanOperation": -1,
  "clippingMaskMode": 0,
  "do_objectID": "70072356-FB10-4A32-9542-2289BF83EA95",
  "exportOptions": {
    "_class": "exportOptions",
    "do_objectID": "806E26B8-D01C-48AE-88A1-52C91AE015A3",
    "exportFormats": [
    ],
    "includedLayerIds": [
    ],
    "layerOptions": 0,
    "shouldTrim": false
  },
  "frame": {
    "_class": "rect",
    "constrainProportions": false,
    "do_objectID": "3AA5E46C-98C2-4128-A2E9-CBDC01B80D68",
    "height": 21,
    "width": 39,
    "x": 168,
    "y": 623
  },
  "hasClippingMask": false,
  "horizontalSpacing": 0,
  "isFixedToViewport": false,
  "isFlippedHorizontal": false,
  "isFlippedVertical": false,
  "isLocked": false,
  "isVisible": true,
  "layerListExpandedType": 0,
  "name": "molecule / help copy 3",
  "nameIsFixed": false,
  "overrideValues": [
  ],
  "resizingConstraint": 63,
  "resizingType": 0,
  "rotation": 0,
  "scale": 1,
  "shouldBreakMaskChain": false,
  "style": {
    "_class": "style",
    "do_objectID": "96E07313-B68D-4DE1-98DF-4C58D9F52585",
    "endMarkerType": 0,
    "miterLimit": 10,
    "startMarkerType": 0,
    "windingRule": 1
  },
  "symbolID": "3B988D48-1194-4C9D-B881-53768E9C8A4B",
  "verticalSpacing": 0
}